{
   "error": "false",
   "filename": "Atom_2.6.3_cedric-10.0-20200505-0623-OFFICIAL.zip",
   "datetime": 1588659716,
   "size": 1423712010,
   "url": "https://sourceforge.net/projects/atom-os-project/files/cedric/Atom_2.6.3_cedric-10.0-20200505-0623-OFFICIAL.zip/download",
   "filehash": "3b8d69139a454c0afce31f32e4f06601",
   "version": "ten",
   "id": "0b3c3cc40940ea65c4537b189b8a0c60faa5c0215a29ef8b4a66863007927bfd",
   "website_url": "",
   "news_url": "",
   "donate_url": "",
   "maintainer": "kiam001",
   "maintainer_url": "",
   "telegram_username": "kiam001",
   "forum_url": ""
}
