{
   "error": "false",
   "filename": "Atom_2.6.3_daisy-10.0-20200509-0439-OFFICIAL.zip",
   "datetime": "1588998989",
   "size": 1261775431 ,
   "url": "https://sourceforge.net/projects/atom-os-project/files/daisy/Atom_2.6.3_daisy-10.0-20200509-0439-OFFICIAL.zip/download",
   "filehash": "6528a696eb319e8f6b521f40a223d5b9",
   "version": "ten",
   "id": "297592fe433d04b659f31408e48bd1c95b403273f356585e3ec403389d19e239",
   "website_url": "",
   "news_url": "",
   "donate_url": "",
   "maintainer": "ScaryMen1325",
   "maintainer_url": "https://github.com/scarymen1325",
   "telegram_username": "scarymen1325",
   "forum_url": ""
}
